iinvestpy/__init__.py
iinvestpy/calculos.py
iinvestpy/dados.py
iinvestpy/visualizacao.py
iinvestimentpy-1.0.2.dist-info/METADATA
iinvestimentpy-1.0.2.dist-info/WHEEL
iinvestimentpy-1.0.2.dist-info/top_level.txt
iinvestimentpy-1.0.2.dist-info/RECORD
